genism/__init__.py
genism/core.py
coher-0.1.0.dist-info/METADATA
coher-0.1.0.dist-info/WHEEL
coher-0.1.0.dist-info/top_level.txt
coher-0.1.0.dist-info/RECORD
