Metadata-Version: 2.1
Name: coher
Version: 0.1.0
Summary: A Python library by Unknown
Author: Unknown
Author-email: 123@email.com
Requires-Python: >=3.6
